pinecone_datasets/__init__.py
pinecone_datasets/catalog.py
pinecone_datasets/cfg.py
pinecone_datasets/dataset.py
pinecone_datasets/dataset_fsreader.py
pinecone_datasets/dataset_fswriter.py
pinecone_datasets/dataset_metadata.py
pinecone_datasets/fs.py
pinecone_datasets/public.py
pinecone_datasets/tqdm.py
pinecone_datasets/utils.py
pinecone_datasets-1.0.2.dist-info/METADATA
pinecone_datasets-1.0.2.dist-info/WHEEL
pinecone_datasets-1.0.2.dist-info/RECORD
