Metadata-Version: 2.1
Name: pinecone-datasets
Version: 1.0.2
Summary: Load datasets to explore Pinecone
Author: Pinecone Support
Author-email: support@pinecone.io
Maintainer: Amnon Catav
Maintainer-email: amnon@pinecone.io
Requires-Python: >=3.9,<3.14
Classifier: Programming Language :: Python :: 3
Classifier: Programming Language :: Python :: 3.9
Classifier: Programming Language :: Python :: 3.10
Classifier: Programming Language :: Python :: 3.11
Requires-Dist: fsspec (>=2025.2.0,<2026.0.0)
Requires-Dist: gcsfs (>=2025.2.0,<2026.0.0)
Requires-Dist: pandas (>=2.0.0,<3.0.0)
Requires-Dist: pyarrow (>=18.0.0,<19.0.0)
Requires-Dist: pydantic (>=2.0.0,<3.0.0)
Requires-Dist: s3fs (>=2025.2.0,<2026.0.0)
